mem8/__init__.py
mem8/__main__.py
mem8/claude_integration.py
mem8/cli_entry.py
mem8/cli_typer.py
mem8/cli/__init__.py
mem8/cli/__main__.py
mem8/cli/actions.py
mem8/cli/main.py
mem8/cli/state.py
mem8/cli/types.py
mem8/cli/utils.py
mem8/cli/commands/__init__.py
mem8/cli/commands/core.py
mem8/cli/commands/deploy.py
mem8/cli/commands/find.py
mem8/cli/commands/init.py
mem8/cli/commands/metadata.py
mem8/cli/commands/team.py
mem8/cli/commands/templates.py
mem8/cli/commands/utilities.py
mem8/cli/commands/worktree.py
mem8/core/__init__.py
mem8/core/completion_analysis.py
mem8/core/config.py
mem8/core/intelligent_query.py
mem8/core/memory.py
mem8/core/metadata.py
mem8/core/ports.py
mem8/core/smart_setup.py
mem8/core/sync.py
mem8/core/template_source.py
mem8/core/templates.py
mem8/core/thought_actions.py
mem8/core/thought_discovery.py
mem8/core/thought_entity.py
mem8/core/toolbelt.py
mem8/core/utils.py
mem8/core/worktree.py
mem8/integrations/github.py
mem8-6.0.0.dist-info/METADATA
mem8-6.0.0.dist-info/WHEEL
mem8-6.0.0.dist-info/entry_points.txt
mem8-6.0.0.dist-info/licenses/LICENSE
mem8-6.0.0.dist-info/RECORD
