Metadata-Version: 2.4
Name: mem8
Version: 6.0.0
Summary: Context management toolkit for AI-assisted development
Project-URL: Homepage, https://github.com/killerapp/mem8
Project-URL: Documentation, https://github.com/killerapp/mem8#readme
Project-URL: Repository, https://github.com/killerapp/mem8
Project-URL: Issues, https://github.com/killerapp/mem8/issues
Author-email: killerapp <vaskin@gmail.com>
License: Apache-2.0
License-File: LICENSE
Keywords: ai-development,claude-code,context-management,memory,port-management,templates,toolbelt
Classifier: Development Status :: 4 - Beta
Classifier: Intended Audience :: Developers
Classifier: License :: OSI Approved :: Apache Software License
Classifier: Programming Language :: Python :: 3
Classifier: Programming Language :: Python :: 3.11
Classifier: Programming Language :: Python :: 3.12
Classifier: Topic :: Documentation
Classifier: Topic :: Software Development :: Libraries :: Python Modules
Classifier: Topic :: Text Processing
Requires-Python: >=3.11
Requires-Dist: click>=8.1.0
Requires-Dist: colorama>=0.4.6
Requires-Dist: cookiecutter>=2.4.0
Requires-Dist: fastapi>=0.118.0
Requires-Dist: gitpython>=3.1.0
Requires-Dist: packaging>=23.0
Requires-Dist: pathlib>=1.0.0
Requires-Dist: platformdirs>=3.0.0
Requires-Dist: psutil>=5.9.0
Requires-Dist: pydantic>=2.0.0
Requires-Dist: pyyaml>=6.0
Requires-Dist: requests>=2.28.0
Requires-Dist: rich>=13.0.0
Requires-Dist: typer>=0.9.0
Requires-Dist: uvicorn>=0.37.0
Requires-Dist: watchdog>=3.0.0
Provides-Extra: dev
Requires-Dist: black>=23.0.0; extra == 'dev'
Requires-Dist: build>=1.0.0; extra == 'dev'
Requires-Dist: isort>=5.0.0; extra == 'dev'
Requires-Dist: mypy>=1.0.0; extra == 'dev'
Requires-Dist: pytest-cov>=4.0.0; extra == 'dev'
Requires-Dist: pytest-html>=4.0.0; extra == 'dev'
Requires-Dist: pytest-xdist>=3.0.0; extra == 'dev'
Requires-Dist: pytest>=7.0.0; extra == 'dev'
Requires-Dist: python-semantic-release>=9.0.0; extra == 'dev'
Provides-Extra: semantic
Requires-Dist: sentence-transformers>=2.2.0; extra == 'semantic'
Provides-Extra: server
Requires-Dist: aiosqlite>=0.19.0; extra == 'server'
Requires-Dist: alembic>=1.12.0; extra == 'server'
Requires-Dist: asyncpg>=0.29.0; extra == 'server'
Requires-Dist: email-validator>=2.1.0; extra == 'server'
Requires-Dist: httpx>=0.25.0; extra == 'server'
Requires-Dist: passlib[bcrypt]>=1.7.4; extra == 'server'
Requires-Dist: prometheus-client>=0.19.0; extra == 'server'
Requires-Dist: pydantic-settings>=2.0.0; extra == 'server'
Requires-Dist: pyjwt>=2.8.0; extra == 'server'
Requires-Dist: python-jose[cryptography]>=3.3.0; extra == 'server'
Requires-Dist: python-json-logger>=2.0.7; extra == 'server'
Requires-Dist: python-multipart>=0.0.6; extra == 'server'
Requires-Dist: redis>=5.0.0; extra == 'server'
Requires-Dist: sqlalchemy>=2.0.0; extra == 'server'
Requires-Dist: websockets>=12.0; extra == 'server'
